{
  "bundle_metadata": {
    "bundle_id": "previous-papers-v1.0",
    "version": "1.0",
    "created_date": "2025-10-31",
    "description": "Curated collection of CBT1 and CBT2 previous year question papers for RRB NTPC exam preparation",
    "target_audience": "RRB NTPC exam aspirants",
    "manifest_format": "JSON",
    "validation_schema": "openzim-bundle-v1.0"
  },
  "bundle_configuration": {
    "language_support": ["en", "hi"],
    "total_content_size": "2.5 GB",
    "estimated_article_count": 1500,
    "compression_level": "max",
    "indexing_strategy": "full_text",
    "build_priority": "high"
  },
  "content_sources": {
    "rrb_official_papers": {
      "source_path": "/workspace/content/rrb-ntpc/previous-papers/",
      "includes": ["CBT1/", "CBT2/"],
      "content_types": ["PDF", "JPG", "PNG"],
      "licensing": "government-work",
      "attribution_required": true,
      "priority": "primary"
    },
    "practice_sets": {
      "source_path": "/workspace/practice-ga/previous-year-papers/",
      "content_types": ["PDF", "DOC"],
      "licensing": "mixed",
      "attribution_required": true,
      "priority": "secondary"
    }
  },
  "metadata_inclusion": {
    "required_fields": [
      "paper_year",
      "exam_stage",
      "subject",
      "medium",
      "difficulty_level",
      "question_type",
      "page_count"
    ],
    "enrichment_sources": [
      "/workspace/diksha-ga/metadata/",
      "/workspace/metadata/official_papers_catalog.csv",
      "/workspace/metadata/rrb_sources_catalog.csv"
    ]
  },
  "compression_settings": {
    "pdf_compression": "aggressive",
    "image_compression": "webp",
    "document_compression": "gzip",
    "compression_tools": ["qpdf", "ghostscript", "imagemagick"],
    "preserve_quality": false
  },
  "indexing_requirements": {
    "search_fields": [
      "title",
      "subject",
      "year",
      "exam_stage",
      "difficulty_level",
      "keywords"
    ],
    "full_text_search": true,
    "language_specific_indexing": true,
    "tag_based_indexing": [
      "CBT1", "CBT2", "English", "Hindi", 
      "Mathematics", "Reasoning", "General Awareness"
    ]
  },
  "licensing_compliance": {
    "cc_by_content": {
      "source": "DIKSHA Platform",
      "license": "CC BY 4.0",
      "share_alike": false,
      "commercial_use": true
    },
    "government_work": {
      "source": "RRB Official",
      "license": "Government Work",
      "commercial_use": true
    },
    "restricted_content": {
      "source": "Third-party platforms",
      "license": "All Rights Reserved",
      "redistribution": false,
      "personal_use_only": true
    }
  },
  "pwa_integration": {
    "offline_capability": true,
    "sync_strategy": "selective",
    "cache_size_limit": "1.5 GB",
    "update_frequency": "quarterly",
    "prefetch_strategy": "search-based"
  },
  "quality_assurance": {
    "file_integrity": true,
    "duplicate_removal": true,
    "format_validation": true,
    "accessibility_compliance": "WCAG 2.1 AA"
  },
  "build_configuration": {
    "output_format": "zim",
    "chunk_size": "100 MB",
    "parallel_processing": 8,
    "build_timeout": "4 hours",
    "verification_level": "strict"
  }
}